taxonize_gb/__init__.py
taxonize_gb/get_db.py
taxonize_gb/get_taxonomy.py
taxonize_gb/main.py
taxonize_gb/taxonize_gb.py
taxonize_gb/test_main.py
taxonize_gb/utils/__init__.py
taxonize_gb/utils/filter_utils.py
taxonize_gb/utils/get_db.py
taxonize_gb/utils/get_taxonomy.py
taxonize_gb/utils/taxonomy_utils.py
taxonize_gb-1.1.16.dist-info/LICENSE
taxonize_gb-1.1.16.dist-info/METADATA
taxonize_gb-1.1.16.dist-info/WHEEL
taxonize_gb-1.1.16.dist-info/entry_points.txt
taxonize_gb-1.1.16.dist-info/top_level.txt
taxonize_gb-1.1.16.dist-info/RECORD
