Metadata-Version: 2.1
Name: taxonize_gb
Version: 1.1.16
Summary: Python package to download and filter GenBank database based on taxonomy
Home-page: https://github.com/msabrysarhan/taxonize_genbank
Author: Mohamed S. Sarhan
Author-email: mohamed.sarhan@eurac.edu
License: Creative Commons Attribution-NonCommercial 4.0 International License (CC BY-NC 4.0)
License-File: LICENSE
Requires-Dist: biopython >=1.67
Requires-Dist: tqdm >=4.62.3
Requires-Dist: ete3 >=3.1.0
Requires-Dist: networkx >=2.6.2
Requires-Dist: six >=1.16.0
Requires-Dist: isal >=1.7.1
